voicegram/__init__.py
voicegram/core.py
voicegram-0.0.1.dist-info/METADATA
voicegram-0.0.1.dist-info/WHEEL
voicegram-0.0.1.dist-info/licenses/LICENSE
voicegram-0.0.1.dist-info/RECORD
