Metadata-Version: 2.4
Name: voicegram
Version: 0.0.1
Summary: Lightweight Python library that turns any audio file into a Telegram voice note (.ogg/Opus) — and back.
Project-URL: Homepage, https://github.com/frymex/voicegram
Project-URL: Changelog, https://github.com/frymex/voicegram/blob/main/CHANGELOG.md
Project-URL: Issues, https://github.com/frymex/voicegram/issues
Author-email: Nikita Protect <t_frymex@proton.me>
License: MIT
License-File: LICENSE
Classifier: Intended Audience :: Developers
Classifier: License :: OSI Approved :: MIT License
Classifier: Programming Language :: Python :: 3
Classifier: Topic :: Multimedia :: Sound/Audio
Requires-Python: >=3.9
Requires-Dist: opuslib>=3.0
Requires-Dist: pydub>=0.25
